wolfsoftware/magic8ball/__init__.py
wolfsoftware/magic8ball/exceptions.py
wolfsoftware/magic8ball/magic8ball.py
wolfsoftware.magic8ball-0.1.0.dist-info/LICENSE.md
wolfsoftware.magic8ball-0.1.0.dist-info/METADATA
wolfsoftware.magic8ball-0.1.0.dist-info/WHEEL
wolfsoftware.magic8ball-0.1.0.dist-info/top_level.txt
wolfsoftware.magic8ball-0.1.0.dist-info/RECORD
